AirPackages/AirPackages.py
AirPackages/__init__.py
AirPackages/__main__.py
AirPackages/cli.py
AirPackages/utils.py
airpackages-0.1.0.dist-info/licenses/LICENSE
airpackages-0.1.0.dist-info/METADATA
airpackages-0.1.0.dist-info/WHEEL
airpackages-0.1.0.dist-info/entry_points.txt
airpackages-0.1.0.dist-info/top_level.txt
airpackages-0.1.0.dist-info/RECORD
